tkitKeyBertBackend/TransformersBackend.py
tkitKeyBertBackend/__init__.py
tkitKeyBertBackend-0.0.1.dist-info/LICENSE
tkitKeyBertBackend-0.0.1.dist-info/METADATA
tkitKeyBertBackend-0.0.1.dist-info/WHEEL
tkitKeyBertBackend-0.0.1.dist-info/top_level.txt
tkitKeyBertBackend-0.0.1.dist-info/RECORD
